longest_increasing_subsequence/__init__.py
longest_increasing_subsequence/_implementation.py
longest_increasing_subsequence-0.1.7.dist-info/AUTHORS.rst
longest_increasing_subsequence-0.1.7.dist-info/LICENSE
longest_increasing_subsequence-0.1.7.dist-info/METADATA
longest_increasing_subsequence-0.1.7.dist-info/WHEEL
longest_increasing_subsequence-0.1.7.dist-info/top_level.txt
longest_increasing_subsequence-0.1.7.dist-info/RECORD
