Metadata-Version: 1.2
Name: longest-increasing-subsequence
Version: 0.1.7
Summary: Find the longest increasing or decreasing subsequence of a sequence.
Home-page: https://github.com/mCodingLLC/longest_increasing_subsequence
Author: James Murphy
Author-email: james@mcoding.io
License: MIT license
Keywords: longest_increasing_subsequence
Platform: UNKNOWN
Classifier: Development Status :: 2 - Pre-Alpha
Classifier: Intended Audience :: Developers
Classifier: License :: OSI Approved :: MIT License
Classifier: Natural Language :: English
Classifier: Programming Language :: Python :: 3
Classifier: Programming Language :: Python :: 3.6
Classifier: Programming Language :: Python :: 3.7
Classifier: Programming Language :: Python :: 3.8
Classifier: Programming Language :: Python :: 3.9
Requires-Python: >=3.6
